jk_dirwalker/DescendFilter.py
jk_dirwalker/DirEntryX.py
jk_dirwalker/DirWalker.py
jk_dirwalker/EmitFilter.py
jk_dirwalker/EnableEmitFilter.py
jk_dirwalker/FileExtEmitFilter.py
jk_dirwalker/FileNameEmitFilter.py
jk_dirwalker/StdEmitFilter.py
jk_dirwalker/_WalkCtx.py
jk_dirwalker/__init__.py
jk_dirwalker-0.2024.7.13.dist-info/WHEEL
jk_dirwalker-0.2024.7.13.dist-info/METADATA
jk_dirwalker-0.2024.7.13.dist-info/RECORD
