Metadata-Version: 2.1
Name: jk_dirwalker
Version: 0.2024.7.13
Summary: Recursively iterates over files and directories in a directory tree
Keywords: 
Author-email: Jürgen Knauth <pubsrc@binary-overflow.de>
Maintainer-email: Jürgen Knauth <pubsrc@binary-overflow.de>
Requires-Python: >=3.8
Classifier: Development Status :: 5 - Production/Stable
Classifier: License :: OSI Approved :: Apache Software License
Classifier: Programming Language :: Python :: 3
Requires-Dist: jk_typing
Requires-Dist: jk_prettyprintobj
